MANIFEST.in
setup.py
benchmarks/CMakeLists.txt
benchmarks/sample_assignment_from_py.cc
benchmarks/sample_from_scores.cc
benchmarks/special.cc
derivations/betabinomial.py
derivations/clustering.py
derivations/logbeta.py
derivations/loggamma.py
distributions/__init__.py
distributions/__main__.py
distributions/fileutil.py
distributions/mixins.py
distributions/schema.proto
distributions/schema_pb2.py
distributions/sparse_counter.pxd
distributions/util.py
distributions/dbg/__init__.py
distributions/dbg/random.py
distributions/dbg/special.py
distributions/dbg/models/__init__.py
distributions/dbg/models/dd.py
distributions/dbg/models/dpd.py
distributions/dbg/models/gp.py
distributions/dbg/models/nich.py
distributions/hp/__init__.py
distributions/hp/random.pxd
distributions/hp/random.pyx
distributions/hp/special.pxd
distributions/hp/special.pyx
distributions/hp/models/__init__.py
distributions/hp/models/dd.pyx
distributions/hp/models/dpd.pyx
distributions/hp/models/gp.pyx
distributions/hp/models/nich.pyx
distributions/lp/__init__.py
distributions/lp/clustering.pyx
distributions/lp/random.pxd
distributions/lp/random.pyx
distributions/lp/special.pyx
distributions/lp/vector.pxd
distributions/lp/vector.pyx
distributions/lp/models/__init__.py
distributions/lp/models/dd.pyx
distributions/lp/models/dpd.pyx
distributions/lp/models/gp.pyx
distributions/lp/models/nich.pyx
distributions/tests/__init__.py
distributions/tests/test_clustering.py
distributions/tests/test_fileutil.py
distributions/tests/test_model_flavors.py
distributions/tests/test_models.py
distributions/tests/test_random.py
distributions/tests/test_special.py
distributions/tests/test_util.py
distributions/tests/util.py
doc/references.bib
examples/cmake/CMakeLists.txt
examples/cmake/foo.cc
include/distributions/aligned_allocator.hpp
include/distributions/clustering.hpp
include/distributions/common.hpp
include/distributions/random.hpp
include/distributions/random_fwd.hpp
include/distributions/schema.pb.h
