Metadata-Version: 1.0
Name: distributions
Version: 2.0.0
Summary: Primitives for Bayesian MCMC inference
Home-page: https://github.com/forcedotcom/distributions
Author: Fritz Obermeyer
Author-email: fobermeyer@salesforce.com
License: Revised BSD
Platform: UNKNOWN
